DeskWebLib/__init__.py
DeskWebLib/desktop_keywords.py
DeskWebLib/utils.py
DeskWebLib/web_keywords.py
deskweblib-0.1.0.dist-info/licenses/LICENSE
deskweblib-0.1.0.dist-info/METADATA
deskweblib-0.1.0.dist-info/WHEEL
deskweblib-0.1.0.dist-info/top_level.txt
deskweblib-0.1.0.dist-info/RECORD
