Metadata-Version: 2.4
Name: DeskWebLib
Version: 0.1.0
Summary: Hybrid Robot Framework library for web and desktop automation
Home-page: https://github.com/Reshma1410/deskweblib/tree/master
Author: Reshma Banu
License: MIT
Classifier: Programming Language :: Python :: 3
Classifier: Framework :: Robot Framework
Classifier: Operating System :: OS Independent
Requires-Python: >=3.6
License-File: LICENSE
Requires-Dist: robotframework
Requires-Dist: selenium
Requires-Dist: pyautogui
Requires-Dist: pillow
Requires-Dist: opencv-python
Requires-Dist: numpy
Dynamic: author
Dynamic: classifier
Dynamic: description
Dynamic: description-content-type
Dynamic: home-page
Dynamic: license
Dynamic: license-file
Dynamic: requires-dist
Dynamic: requires-python
Dynamic: summary
